SecQureSdk/__init__.py
SecQureSdk/accessToken.py
SecQureSdk/idToken.py
SecQureSdk/renewToken.py
pySdk/__init__.py
pySdk/accessToken.py
pySdk/idToken.py
pySdk/renewToken.py
secuuthSdk/__init__.py
secuuthSdk/accessToken.py
secuuthSdk/idToken.py
secuuthSdk/renewToken.py
SecQurePythonSdk-3.0.dist-info/LICENSE
SecQurePythonSdk-3.0.dist-info/METADATA
SecQurePythonSdk-3.0.dist-info/WHEEL
SecQurePythonSdk-3.0.dist-info/top_level.txt
SecQurePythonSdk-3.0.dist-info/RECORD
